.pre-commit-config.yaml
CHANGES.SIMD.rst
CHANGES.rst
LICENSE
MANIFEST.in
Makefile
PyPI.rst
README.md
RELEASING.md
conftest.py
run.py
selftest.py
setup.cfg
setup.py
tox.ini
depends/README.rst
depends/download-and-extract.sh
depends/install_extra_test_images.sh
depends/install_imagequant.sh
depends/install_openjpeg.sh
depends/install_raqm.sh
depends/install_raqm_cmake.sh
depends/install_webp.sh
depends/termux.sh
docs/COPYING
docs/Guardfile
docs/Makefile
docs/PIL.rst
docs/about.rst
docs/conf.py
docs/deprecations.rst
docs/index.rst
docs/installation.rst
docs/make.bat
docs/newer-versions.csv
docs/older-versions.csv
docs/porting.rst
docs/example/DdsImagePlugin.py
docs/example/anchors.png
docs/example/anchors.py
docs/handbook/appendices.rst
docs/handbook/concepts.rst
docs/handbook/image-file-formats.rst
docs/handbook/index.rst
docs/handbook/overview.rst
docs/handbook/text-anchors.rst
docs/handbook/tutorial.rst
docs/handbook/writing-your-own-image-plugin.rst
docs/reference/ExifTags.rst
docs/reference/Image.rst
docs/reference/ImageChops.rst
docs/reference/ImageCms.rst
docs/reference/ImageColor.rst
docs/reference/ImageDraw.rst
docs/reference/ImageEnhance.rst
docs/reference/ImageFile.rst
docs/reference/ImageFilter.rst
docs/reference/ImageFont.rst
docs/reference/ImageGrab.rst
docs/reference/ImageMath.rst
docs/reference/ImageMorph.rst
docs/reference/ImageOps.rst
docs/reference/ImagePalette.rst
docs/reference/ImagePath.rst
docs/reference/ImageQt.rst
docs/reference/ImageSequence.rst
docs/reference/ImageShow.rst
docs/reference/ImageStat.rst
docs/reference/ImageTk.rst
docs/reference/ImageWin.rst
docs/reference/JpegPresets.rst
docs/reference/PSDraw.rst
docs/reference/PixelAccess.rst
docs/reference/PyAccess.rst
docs/reference/TiffTags.rst
docs/reference/block_allocator.rst
docs/reference/c_extension_debugging.rst
docs/reference/features.rst
docs/reference/index.rst
docs/reference/internal_design.rst
docs/reference/internal_modules.rst
docs/reference/limits.rst
src/Pillow_SIMD.egg-info/PKG-INFO
src/Pillow_SIMD.egg-info/SOURCES.txt
src/Pillow_SIMD.egg-info/dependency_links.txt
src/Pillow_SIMD.egg-info/requires.txt
src/Pillow_SIMD.egg-info/top_level.txt
src/Pillow_SIMD.egg-info/zip-safe
