Metadata-Version: 2.1
Name: Pillow-SIMD
Version: 9.5.0.post1
Summary: Python Imaging Library (Fork)
Home-page: https://github.com/uploadcare/pillow-simd
Author: Jeffrey A. Clark (Alex)
Author-email: aclark@aclark.net
License: HPND
Project-URL: Documentation, https://pillow.readthedocs.io
Project-URL: Source, https://github.com/uploadcare/pillow-simd
Project-URL: Funding, https://tidelift.com/subscription/pkg/pypi-pillow?utm_source=pypi-pillow&utm_medium=pypi
Project-URL: Release notes, https://pillow.readthedocs.io/en/stable/releasenotes/index.html
Project-URL: Changelog, https://github.com/python-pillow/Pillow/blob/main/CHANGES.rst
Project-URL: Twitter, https://twitter.com/PythonPillow
Project-URL: Mastodon, https://fosstodon.org/@pillow
Keywords: Imaging
Platform: UNKNOWN
Classifier: Development Status :: 6 - Mature
Classifier: License :: OSI Approved :: Historical Permission Notice and Disclaimer (HPND)
Classifier: Programming Language :: Python :: 3
Classifier: Programming Language :: Python :: 3 :: Only
Classifier: Programming Language :: Python :: 3.7
Classifier: Programming Language :: Python :: 3.8
Classifier: Programming Language :: Python :: 3.9
Classifier: Programming Language :: Python :: 3.10
Classifier: Programming Language :: Python :: 3.11
Classifier: Programming Language :: Python :: Implementation :: CPython
Classifier: Programming Language :: Python :: Implementation :: PyPy
Classifier: Topic :: Multimedia :: Graphics
Classifier: Topic :: Multimedia :: Graphics :: Capture :: Digital Camera
Classifier: Topic :: Multimedia :: Graphics :: Capture :: Screen Capture
Classifier: Topic :: Multimedia :: Graphics :: Graphics Conversion
Classifier: Topic :: Multimedia :: Graphics :: Viewers
Requires-Python: >=3.7
Provides-Extra: docs
Provides-Extra: tests
